rubixs/__init__.py
rubixs/cube.py
rubixs-0.0.1.dist-info/LICENSE
rubixs-0.0.1.dist-info/METADATA
rubixs-0.0.1.dist-info/WHEEL
rubixs-0.0.1.dist-info/top_level.txt
rubixs-0.0.1.dist-info/RECORD
